contract_reviewer/contractreviewer.py
contract_reviewer-0.0.8.dist-info/entry_points.txt
contract_reviewer-0.0.8.dist-info/WHEEL
contract_reviewer-0.0.8.dist-info/METADATA
contract_reviewer-0.0.8.dist-info/RECORD
